ontology_processing/__init__.py
ontology_processing/process_new_ontology_file.py
ontology_processing/graph_creation/__init__.py
ontology_processing/graph_creation/make_graph.py
ontology_processing/graph_creation/make_graph_class.py
ontology_processing/graph_creation/make_network.py
ontology_processing/graph_creation/network_class.py
ontology_processing/graph_creation/ontology_processing_utils.py
ontology_processing/graph_creation/process_causal_sources.py
ontology_processing/graph_creation/process_myths.py
ontology_processing/graph_creation/process_visualization.py
ontology_processing/visualize/__init__.py
ontology_processing/visualize/visualize.py
ontology_processing-1.0.8.data/scripts/process_new_ontology_file.py
ontology_processing-1.0.8.dist-info/LICENSE
ontology_processing-1.0.8.dist-info/METADATA
ontology_processing-1.0.8.dist-info/WHEEL
ontology_processing-1.0.8.dist-info/top_level.txt
ontology_processing-1.0.8.dist-info/RECORD
